DataframeFormatterSC/__init__.py
DataframeFormatterSC/dataframeStyler.py
dataframeformattersc-0.0.1.dist-info/METADATA
dataframeformattersc-0.0.1.dist-info/WHEEL
dataframeformattersc-0.0.1.dist-info/licenses/LICENSE.txt
dataframeformattersc-0.0.1.dist-info/RECORD
