Metadata-Version: 2.1
Name: DataframeFormatterSC
Version: 0.0.1
Summary: A dataframe formatting tool
Project-URL: Homepage, https://github.com/SimoneCallegarin/DataframeFormatting
Author-email: SimoneCallegarin <simone.callegarin00@gmail.com>
License-File: LICENSE.txt
Classifier: License :: OSI Approved :: MIT License
Classifier: Operating System :: OS Independent
Classifier: Programming Language :: Python :: 3
Requires-Python: >=3.7
